tilty/__init__.py
tilty/blescan.py
tilty/cli.py
tilty/common.py
tilty/constants.py
tilty/exceptions.py
tilty/tilt_device.py
tilty/tilty.py
tilty/emitters/__init__.py
tilty/emitters/datadog.py
tilty/emitters/google.py
tilty/emitters/influxdb.py
tilty/emitters/prometheus.py
tilty/emitters/sqlite.py
tilty/emitters/stdout.py
tilty/emitters/webhook.py
Tilty-0.12.0.dist-info/LICENSE
Tilty-0.12.0.dist-info/METADATA
Tilty-0.12.0.dist-info/WHEEL
Tilty-0.12.0.dist-info/entry_points.txt
Tilty-0.12.0.dist-info/top_level.txt
Tilty-0.12.0.dist-info/RECORD
