Metadata-Version: 2.1
Name: Tilty
Version: 0.12.0
Summary: A pluggable system to receive and transmit bluetooth events from the Tilt Hydrometer
Home-page: UNKNOWN
Author: Marcus Young
Author-email: 3vilpenguin@gmail.com
License: UNKNOWN
Platform: UNKNOWN
Requires-Dist: click (==7.1.2)
Requires-Dist: datadog (==0.34.1)
Requires-Dist: influxdb-client (==1.17.0)
Requires-Dist: jinja2 (==3.0.1)
Requires-Dist: prometheus-client (==0.8.0)
Requires-Dist: pybluez (==0.22)
Requires-Dist: requests (==2.25.1)
Requires-Dist: urllib3 (>=1.26.5)
Requires-Dist: google-auth (==1.30.1)
Requires-Dist: google-api-core (==1.20.1)
Requires-Dist: google-api-python-client (==1.11.0)
Requires-Dist: google-auth-httplib2 (==0.0.4)
Requires-Dist: google-auth-oauthlib (==0.4.4)
Requires-Dist: oauth2client (==4.1.3)
Requires-Dist: protobuf (==3.17.2)
